metacity-0.6.2.dist-info/top_level.txt
metacity-0.6.2.dist-info/LICENCE
metacity-0.6.2.dist-info/METADATA
metacity-0.6.2.dist-info/RECORD
metacity-0.6.2.dist-info/WHEEL
metacity.libs/libgcc_s-a04fdf82.so.1
metacity.libs/libstdc++-a9383cce.so.6.0.28
metacity/__main__.py
metacity/geometry.cpython-38-x86_64-linux-gnu.so
metacity/__init__.py
metacity/io/shapefile.py
metacity/io/geojson.py
metacity/io/__init__.py
metacity/io/obj.py
metacity/io/convert.py
metacity/io/geobuf/decode.py
metacity/io/geobuf/__init__.py
metacity/io/geobuf/geobuf_pb2.py
metacity/io/geobuf/encode.py
metacity/io/pyshp/pyshp.py
metacity/io/pyshp/__init__.py
metacity/utils/config.py
metacity/utils/__init__.py
metacity/utils/filesystem.py
