Metadata-Version: 2.1
Name: metacity
Version: 0.6.2
Summary: Python toolkit for Urban Data processing
Home-page: https://github.com/MetacitySuite/Metacity
Author: Vojtěch Tomas
Author-email: hello@vojtatom.cz
License: MIT
Classifier: License :: OSI Approved :: MIT License
Classifier: Programming Language :: Python :: 3
Classifier: Programming Language :: Python :: 3.8
Requires-Python: >=3.8
License-File: LICENCE
